s1_lia/__init__.py
s1_lia/app.py
s1_lia/download.py
s1_lia/search.py
s1_lia-0.3.1.dist-info/licenses/LICENSE
s1_lia-0.3.1.dist-info/METADATA
s1_lia-0.3.1.dist-info/WHEEL
s1_lia-0.3.1.dist-info/entry_points.txt
s1_lia-0.3.1.dist-info/top_level.txt
s1_lia-0.3.1.dist-info/RECORD
