Metadata-Version: 2.4
Name: s1_lia
Version: 0.3.1
Summary: Search and download OPERA local incidence angle files for Sentinel-1.
Home-page: https://github.com/zachhoppinen/s1_lia
Author: Zachary Hoppinen
Author-email: zachhoppinen@gmail.com
License: MIT
Classifier: Programming Language :: Python :: 3
Classifier: License :: OSI Approved :: MIT License
Classifier: Operating System :: OS Independent
Requires-Python: >=3.7
License-File: LICENSE
Requires-Dist: numpy
Requires-Dist: geopandas
Requires-Dist: shapely
Requires-Dist: asf_search
Requires-Dist: xarray
Requires-Dist: rioxarray
Requires-Dist: requests
Requires-Dist: tqdm
Dynamic: license-file
